data_generation_tool/__init__.py
data_generation_tool/constraints/__init__.py
data_generation_tool/constraints/column_constraints/__init__.py
data_generation_tool/constraints/column_constraints/boolean_constraints.py
data_generation_tool/constraints/column_constraints/column_constraint.py
data_generation_tool/constraints/column_constraints/date_constraints.py
data_generation_tool/constraints/column_constraints/enum_constraints.py
data_generation_tool/constraints/column_constraints/generic_constraints.py
data_generation_tool/constraints/column_constraints/geographic_coordinates_constraints.py
data_generation_tool/constraints/column_constraints/numeric_constraints.py
data_generation_tool/constraints/column_constraints/text_constraints.py
data_generation_tool/constraints/column_constraints/time_constraints.py
data_generation_tool/constraints/dataset_constraints/__init__.py
data_generation_tool/constraints/dataset_constraints/dataset_constraint.py
data_generation_tool/errors/__init__.py
data_generation_tool/errors/unsatisfiable_constraints.py
data_generation_tool/fmkforml/utils.py
data_generation_tool/fmkforml/checkers/__init__.py
data_generation_tool/fmkforml/checkers/fairchecker.py
data_generation_tool/fmkforml/fmk_data/__init__.py
data_generation_tool/fmkforml/fmk_data/fmkdata.py
data_generation_tool/fmkforml/makers/__init__.py
data_generation_tool/fmkforml/makers/fairmaker.py
data_generation_tool/fmkforml/makers/fmk.py
data_generation_tool/generators/__init__.py
data_generation_tool/generators/app_generator.py
data_generation_tool/generators/book_generator.py
data_generation_tool/generators/boolean_generator.py
data_generation_tool/generators/brand_generator.py
data_generation_tool/generators/channel_generator.py
data_generation_tool/generators/city_generator.py
data_generation_tool/generators/column_generator.py
data_generation_tool/generators/condiment_generator.py
data_generation_tool/generators/contextual_generator.py
data_generation_tool-1.1.1.dist-info/LICENSE
data_generation_tool-1.1.1.dist-info/METADATA
data_generation_tool-1.1.1.dist-info/WHEEL
data_generation_tool-1.1.1.dist-info/top_level.txt
data_generation_tool-1.1.1.dist-info/RECORD
