Metadata-Version: 2.1
Name: data_generation_tool
Version: 1.1.1
Summary: A library that provides data generation functionality for AI and data science projects
Author-email: FRIARE <ird@friare.org>
License: BSD-3-Clause
Project-URL: Homepage, https://github.com/friare/data_generation_tool
Project-URL: Issues, https://github.com/friare/data_generation_tool/issues
Keywords: AI,data-generation,fairness
Classifier: Programming Language :: Python :: 3
Classifier: License :: OSI Approved :: MIT License
Classifier: Operating System :: OS Independent
Requires-Python: >=3.8
License-File: LICENSE
Requires-Dist: exrex==0.11.0
Requires-Dist: numpy~=1.26.4
Requires-Dist: spacy~=3.7
Requires-Dist: openai==1.40.6
Requires-Dist: pandas==2.2.2
Requires-Dist: pytest==8.2.2
Requires-Dist: transformers==4.43.3
Requires-Dist: ortools==9.10.4067
Requires-Dist: python-ulid==2.7.0
Requires-Dist: shapely==2.0.6
